websocket_docker/__init__.py
websocket_docker/module1.py
websocket_docker/module2.py
websocket_docker-0.0.2.dist-info/licenses/LICENSE.txt
websocket_docker-0.0.2.dist-info/METADATA
websocket_docker-0.0.2.dist-info/WHEEL
websocket_docker-0.0.2.dist-info/top_level.txt
websocket_docker-0.0.2.dist-info/RECORD
