Metadata-Version: 2.4
Name: websocket-docker
Version: 0.0.2
Summary: Nothing
Author-email: Chuck Knoblauch <knoblauch@gmail.com>
Project-URL: Homepage, https://github.com/knoblauch/nothing
Project-URL: Bug Tracker, https://github.com/knoblauch/nothing/issues
Classifier: Programming Language :: Python :: 3
Classifier: License :: OSI Approved :: MIT License
Classifier: Operating System :: OS Independent
Requires-Python: >=3.7
License-File: LICENSE.txt
Requires-Dist: requests
Dynamic: license-file
